nonebot_plugin_tempfile/__init__.py
nonebot_plugin_tempfile/config.py
nonebot_plugin_tempfile-0.2.0.dist-info/LICENSE
nonebot_plugin_tempfile-0.2.0.dist-info/METADATA
nonebot_plugin_tempfile-0.2.0.dist-info/WHEEL
nonebot_plugin_tempfile-0.2.0.dist-info/top_level.txt
nonebot_plugin_tempfile-0.2.0.dist-info/RECORD
