Metadata-Version: 2.1
Name: nonebot-plugin-tempfile
Version: 0.2.0
Summary: 适用于 NoneBot2 插件的临时文件/IO 依赖注入支持
Author-email: HivertMoZara <worldmozara@163.com>
License: MIT
Project-URL: Homepage, https://github.com/NCBM/nonebot-plugin-tempfile
Project-URL: Repository, https://github.com/NCBM/nonebot-plugin-tempfile
Requires-Python: >=3.8
License-File: LICENSE
Requires-Dist: nonebot2 >=2.2.0
